{
  "parent": "minecraft:recipes/root",
  "rewards": {
    "recipes": [
      "hempfarmer:oily_dirt"
    ]
  },
  "criteria": {
    "oily_burlap": {
      "trigger": "minecraft:inventory_changed",
      "conditions": {
        "items": [
          {
            "items": [
              "hempfarmer:hemp_oil"
            ]
          }
        ]
      }
    },
    "has_the_recipe": {
      "trigger": "minecraft:recipe_unlocked",
      "conditions": {
        "recipe": "hempfarmer:oily_dirt"
      }
    }
  },
  "requirements": [
    [
      "oily_burlap",
      "has_the_recipe"
    ]
  ]
}